sqlsugar/__init__.py
sqlsugar-0.1.dist-info/LICENSE
sqlsugar-0.1.dist-info/METADATA
sqlsugar-0.1.dist-info/WHEEL
sqlsugar-0.1.dist-info/top_level.txt
sqlsugar-0.1.dist-info/RECORD
