Metadata-Version: 2.1
Name: sqlsugar
Version: 0.1
Summary: Automatic migrations for SQLAlchemy
Home-page: https://github.com/Teemu/sqlsugar
Author: Teemu
License: Apache License, Version 2.0
Project-URL: Issues, https://github.com/Teemu/sqlsugar/issues
Project-URL: CI, https://github.com/Teemu/sqlsugar/actions
Project-URL: Changelog, https://github.com/Teemu/sqlsugar/releases
Requires-Python: >=3.7
License-File: LICENSE
Requires-Dist: sqlalchemy
Requires-Dist: alembic
Provides-Extra: test
Requires-Dist: pytest ; extra == 'test'
Requires-Dist: pre-commit ; extra == 'test'
Requires-Dist: pytest-sugar ; extra == 'test'
Requires-Dist: sqlmodel ; extra == 'test'
Requires-Dist: black ; extra == 'test'
Requires-Dist: isort ; extra == 'test'
